odoo/addons/account_cutoff_accrual_sale/README.rst
odoo/addons/account_cutoff_accrual_sale/__init__.py
odoo/addons/account_cutoff_accrual_sale/__manifest__.py
odoo/addons/account_cutoff_accrual_sale/hooks.py
odoo/addons/account_cutoff_accrual_sale/data/ir_cron.xml
odoo/addons/account_cutoff_accrual_sale/i18n/account_cutoff_accrual_sale.pot
odoo/addons/account_cutoff_accrual_sale/i18n/fr.po
odoo/addons/account_cutoff_accrual_sale/i18n/it.po
odoo/addons/account_cutoff_accrual_sale/models/__init__.py
odoo/addons/account_cutoff_accrual_sale/models/account_cutoff.py
odoo/addons/account_cutoff_accrual_sale/models/account_cutoff_line.py
odoo/addons/account_cutoff_accrual_sale/models/account_move.py
odoo/addons/account_cutoff_accrual_sale/models/sale_order.py
odoo/addons/account_cutoff_accrual_sale/models/sale_order_line.py
odoo/addons/account_cutoff_accrual_sale/readme/CONFIGURE.rst
odoo/addons/account_cutoff_accrual_sale/readme/CONTRIBUTORS.rst
odoo/addons/account_cutoff_accrual_sale/readme/DESCRIPTION.rst
odoo/addons/account_cutoff_accrual_sale/static/description/icon.png
odoo/addons/account_cutoff_accrual_sale/static/description/index.html
odoo/addons/account_cutoff_accrual_sale/tests/__init__.py
odoo/addons/account_cutoff_accrual_sale/tests/common.py
odoo/addons/account_cutoff_accrual_sale/tests/test_cutoff_revenue.py
odoo/addons/account_cutoff_accrual_sale/views/account_cutoff.xml
odoo/addons/account_cutoff_accrual_sale/views/account_cutoff_line.xml
odoo_addon_account_cutoff_accrual_sale-16.0.1.1.0.dist-info/METADATA
odoo_addon_account_cutoff_accrual_sale-16.0.1.1.0.dist-info/WHEEL
odoo_addon_account_cutoff_accrual_sale-16.0.1.1.0.dist-info/top_level.txt
odoo_addon_account_cutoff_accrual_sale-16.0.1.1.0.dist-info/RECORD
